[
  {
    "id": "articulatory_apparatus",
    "title": "孝校携笑蝎 孝",
    "icon": "",
    "path": "data/exercises/01_articulatory_apparatus.json"
  },
  {
    "id": "phonatory_apparatus",
    "title": "肖孝蝎 孝 (孝鞋)",
    "icon": "",
    "path": "data/exercises/02_phonatory_apparatus.json"
  },
  {
    "id": "resonator_system",
    "title": "孝携 小小孝",
    "icon": "",
    "path": "data/exercises/03_resonator_system.json"
  },
  {
    "id": "respiratory_system",
    "title": "蝎啸孝鞋携 小小孝",
    "icon": "",
    "path": "data/exercises/04_respiratory_system.json"
  },
  {
    "id": "musculoskeletal_system",
    "title": "-孝鞋蝎 孝",
    "icon": "",
    "path": "data/exercises/05_musculoskeletal_system.json"
  },
  {
    "id": "nervous_system_and_hearing",
    "title": "携 小小孝  小校啸",
    "icon": "",
    "path": "data/exercises/06_nervous_system_and_hearing.json"
  }
]
